<annotation>
	<folder>4</folder>
	<filename>nvc_21817.mp40089.jpeg</filename>
	<path>D:\Рабочий стол\4\nvc_21817.mp40089.jpeg</path>
	<source>
		<database>Unknown</database>
	</source>
	<size>
		<width>640</width>
		<height>480</height>
		<depth>3</depth>
	</size>
	<segmented>0</segmented>
	<object>
		<name>fish</name>
		<pose>Unspecified</pose>
		<truncated>0</truncated>
		<difficult>0</difficult>
		<bndbox>
			<xmin>14</xmin>
			<ymin>180</ymin>
			<xmax>185</xmax>
			<ymax>375</ymax>
		</bndbox>
	</object>
	<object>
		<name>fish</name>
		<pose>Unspecified</pose>
		<truncated>0</truncated>
		<difficult>0</difficult>
		<bndbox>
			<xmin>431</xmin>
			<ymin>20</ymin>
			<xmax>638</xmax>
			<ymax>332</ymax>
		</bndbox>
	</object>
</annotation>
